{
    "url": "https://www12.senado.leg.br/noticias/materias/2026/03/25/girao-pede-ao-stf-a-abertura-da-cpi-do-banco-master",
    "titulo": "Girão pede ao STF a abertura da CPI do Banco Master",
    "descricao": "Em pronunciamento nesta quarta-feira (25), o senador Eduardo Girão (Novo-CE) disse ter acionado o Supremo Tribunal Federal (STF) para garantir a abertura de uma comissão parlamentar de inquérito (CPI) com objetivo de investigar as fraudes no Banco Master, liquidado pelo Banco Central. Segundo o parlamentar, o requerimento de criação da CPI tem apoio da maioria dos senadores.",
    "tags": [
        "Sistema financeiro",
        "Supremo Tribunal Federal (STF)"
    ],
    "texto": "Em pronunciamento nesta quarta-feira (25), o senador Eduardo Girão (Novo-CE) disse ter acionado o Supremo Tribunal Federal (STF) para garantir a abertura de uma comissão parlamentar de inquérito (CPI) com objetivo de investigar as fraudes no Banco Master, liquidado pelo Banco Central. Segundo o parlamentar, o requerimento de criação da CPI tem apoio da maioria dos senadores.\n\n\n— Nós estamos acionando o Supremo Tribunal Federal para abrir a CPI da maior fraude do sistema financeiro do Brasil. Só o meu requerimento tem 51 assinaturas, uma maioria ampla e irrestrita, para se investigar, e o Parlamento jogar luz nas trevas do Banco Master, que vai deixar milhões de brasileiros a ver navios com suas economias, e muitos outros que não têm nada a ver com isso, que não têm dinheiro no Master — disse.\n\n\nGirão afirmou que acionou a Justiça em razão da demora na instalação da comissão parlamentar de inquérito no Senado. Ele cobrou da Presidência da Casa a abertura da CPI. Ele defendeu o avanço das investigações.\n\n\n— A maior fraude do sistema financeiro do Brasil, que com certeza teve apoio de agentes públicos — institutos que deveriam fiscalizar e não fiscalizaram. Nós estamos dando os últimos suspiros aqui! E o pedido de socorro, que é feito para a Presidência da Casa, para deliberar pedidos de impeachment, abrir CPI, abrir CPMI, prorrogar CPMI... Está tudo parado aqui! Essa inércia não é por acaso, porque isso não se justifica! — afirmou.\n\n\nO parlamentar também mencionou a expectativa de julgamento, pelo plenário do Supremo, de decisão do ministro André Mendonça de determinar a prorrogação da CPMI do INSS. Para Girão, uma eventual reversão da decisão pode comprometer as investigações.\n\n\n\n\n\n\n\n\n\n\n\n\n\n\n\n\n\n\n\n\n\n\n\n\n\n\nAgência Senado (Reprodução autorizada mediante citação da Agência Senado)",
    "data": "2026-03-25T17:50:34-03:00"
}